easy_logx/__init__.py
easy_logx/easy_logx.py
easylogx/__init__.py
easylogx/easylogx.py
easylogx-0.0.6.dist-info/LICENSE
easylogx-0.0.6.dist-info/METADATA
easylogx-0.0.6.dist-info/WHEEL
easylogx-0.0.6.dist-info/top_level.txt
easylogx-0.0.6.dist-info/RECORD
